{"version":"0.2","currency":"USD","projects":[{"name":"toninoes/github-actions-terraform-infracost/terraform","metadata":{"path":".","infracostCommand":"breakdown","type":"terraform_dir","branch":"main","commit":"346bd5265db1f768afa607074c73e24e0c42a6ab","commitAuthorName":"Antonio Ruiz","commitAuthorEmail":"toninoes@gmail.com","commitTimestamp":"2022-08-05T10:50:14Z","commitMessage":"Update README.md","vcsRepoUrl":"git@github.com:toninoes/github-actions-terraform-infracost.git","vcsSubPath":"terraform"},"pastBreakdown":{"resources":[],"totalHourlyCost":"0","totalMonthlyCost":"0"},"breakdown":{"resources":[{"name":"aws_instance.web","tags":{"Name":"HelloWorld"},"metadata":{"calls":[{"blockName":"aws_instance.web","filename":"ec2.tf"}],"filename":"ec2.tf"},"hourlyCost":"0.00690547945205479","monthlyCost":"5.041","costComponents":[{"name":"Instance usage (Linux/UNIX, on-demand, t3.nano)","unit":"hours","hourlyQuantity":"1","monthlyQuantity":"730","price":"0.0057","hourlyCost":"0.0057","monthlyCost":"4.161"},{"name":"CPU credits","unit":"vCPU-hours","hourlyQuantity":"0","monthlyQuantity":"0","price":"0.05","hourlyCost":"0","monthlyCost":"0"}],"subresources":[{"name":"root_block_device","metadata":{},"hourlyCost":"0.00120547945205479","monthlyCost":"0.88","costComponents":[{"name":"Storage (general purpose SSD, gp2)","unit":"GB","hourlyQuantity":"0.010958904109589","monthlyQuantity":"8","price":"0.11","hourlyCost":"0.00120547945205479","monthlyCost":"0.88"}]}]},{"name":"aws_s3_bucket.this","tags":{"Environment":"Dev","Name":"Mi bucket"},"metadata":{"calls":[{"blockName":"aws_s3_bucket.this","filename":"s3.tf"}],"filename":"s3.tf"},"hourlyCost":null,"monthlyCost":null,"subresources":[{"name":"Standard","metadata":{},"hourlyCost":null,"monthlyCost":null,"costComponents":[{"name":"Storage","unit":"GB","hourlyQuantity":null,"monthlyQuantity":null,"price":"0.023","hourlyCost":null,"monthlyCost":null},{"name":"PUT, COPY, POST, LIST requests","unit":"1k requests","hourlyQuantity":null,"monthlyQuantity":null,"price":"0.005","hourlyCost":null,"monthlyCost":null},{"name":"GET, SELECT, and all other requests","unit":"1k requests","hourlyQuantity":null,"monthlyQuantity":null,"price":"0.0004","hourlyCost":null,"monthlyCost":null},{"name":"Select data scanned","unit":"GB","hourlyQuantity":null,"monthlyQuantity":null,"price":"0.002","hourlyCost":null,"monthlyCost":null},{"name":"Select data returned","unit":"GB","hourlyQuantity":null,"monthlyQuantity":null,"price":"0.0007","hourlyCost":null,"monthlyCost":null}]}]}],"totalHourlyCost":"0.00690547945205479","totalMonthlyCost":"5.041"},"diff":{"resources":[{"name":"aws_instance.web","tags":{"Name":"HelloWorld"},"metadata":{},"hourlyCost":"0.00690547945205479","monthlyCost":"5.041","costComponents":[{"name":"Instance usage (Linux/UNIX, on-demand, t3.nano)","unit":"hours","hourlyQuantity":"1","monthlyQuantity":"730","price":"0.0057","hourlyCost":"0.0057","monthlyCost":"4.161"},{"name":"CPU credits","unit":"vCPU-hours","hourlyQuantity":"0","monthlyQuantity":"0","price":"0.05","hourlyCost":"0","monthlyCost":"0"}],"subresources":[{"name":"root_block_device","metadata":{},"hourlyCost":"0.00120547945205479","monthlyCost":"0.88","costComponents":[{"name":"Storage (general purpose SSD, gp2)","unit":"GB","hourlyQuantity":"0.010958904109589","monthlyQuantity":"8","price":"0.11","hourlyCost":"0.00120547945205479","monthlyCost":"0.88"}]}]},{"name":"aws_s3_bucket.this","tags":{"Environment":"Dev","Name":"Mi bucket"},"metadata":{},"hourlyCost":"0","monthlyCost":"0","subresources":[{"name":"Standard","metadata":{},"hourlyCost":"0","monthlyCost":"0","costComponents":[{"name":"Storage","unit":"GB","hourlyQuantity":"0","monthlyQuantity":"0","price":"0.023","hourlyCost":"0","monthlyCost":"0"},{"name":"PUT, COPY, POST, LIST requests","unit":"1k requests","hourlyQuantity":"0","monthlyQuantity":"0","price":"0.005","hourlyCost":"0","monthlyCost":"0"},{"name":"GET, SELECT, and all other requests","unit":"1k requests","hourlyQuantity":"0","monthlyQuantity":"0","price":"0.0004","hourlyCost":"0","monthlyCost":"0"},{"name":"Select data scanned","unit":"GB","hourlyQuantity":"0","monthlyQuantity":"0","price":"0.002","hourlyCost":"0","monthlyCost":"0"},{"name":"Select data returned","unit":"GB","hourlyQuantity":"0","monthlyQuantity":"0","price":"0.0007","hourlyCost":"0","monthlyCost":"0"}]}]}],"totalHourlyCost":"0.00690547945205479","totalMonthlyCost":"5.041"},"summary":{"totalDetectedResources":2,"totalSupportedResources":2,"totalUnsupportedResources":0,"totalUsageBasedResources":2,"totalNoPriceResources":0,"unsupportedResourceCounts":{},"noPriceResourceCounts":{}}}],"totalHourlyCost":"0.00690547945205479","totalMonthlyCost":"5.041","pastTotalHourlyCost":"0","pastTotalMonthlyCost":"0","diffTotalHourlyCost":"0.00690547945205479","diffTotalMonthlyCost":"5.041","timeGenerated":"2022-08-05T12:45:15.152241759Z","summary":{"totalDetectedResources":2,"totalSupportedResources":2,"totalUnsupportedResources":0,"totalUsageBasedResources":2,"totalNoPriceResources":0,"unsupportedResourceCounts":{},"noPriceResourceCounts":{}}}